.gitignore
.gitlab-ci.yml
.pylintrc
LICENSE
MANIFEST.in
Makefile
README.md
codecov.yml
pyproject.toml
requirements.txt
setup.cfg
setup.py
validate-codecov-yaml.bash
variables
./variables
.github/workflows/pythonpackage.yml
files/profile
module/__init__.py
module/__main__.py
module/cli/__init__.py
module/cli/cmdproxy.py
module/cli/parser.py
module/main/__init__.py
module/main/piphyperd.py
module/main/py.typed
module/main/release.py
module/tests/__init__.py
module/tests/test_unit.py
piphyperd/__init__.py
piphyperd/__main__.py
piphyperd.egg-info/PKG-INFO
piphyperd.egg-info/SOURCES.txt
piphyperd.egg-info/dependency_links.txt
piphyperd.egg-info/entry_points.txt
piphyperd.egg-info/not-zip-safe
piphyperd.egg-info/requires.txt
piphyperd.egg-info/top_level.txt
piphyperd/cli/__init__.py
piphyperd/cli/cmdproxy.py
piphyperd/cli/parser.py
piphyperd/main/__init__.py
piphyperd/main/piphyperd.py
piphyperd/main/release.py
typings/setuptools/__init__.pyi
typings/setuptools/_deprecation_warning.pyi
typings/setuptools/_imp.pyi
typings/setuptools/archive_util.pyi
typings/setuptools/build_meta.pyi
typings/setuptools/config.pyi
typings/setuptools/dep_util.pyi
typings/setuptools/depends.pyi
typings/setuptools/dist.pyi
typings/setuptools/errors.pyi
typings/setuptools/extension.pyi
typings/setuptools/glob.pyi
typings/setuptools/installer.pyi
typings/setuptools/launch.pyi
typings/setuptools/lib2to3_ex.pyi
typings/setuptools/monkey.pyi
typings/setuptools/msvc.pyi
typings/setuptools/namespaces.pyi
typings/setuptools/package_index.pyi
typings/setuptools/py34compat.pyi
typings/setuptools/sandbox.pyi
typings/setuptools/ssl_support.pyi
typings/setuptools/unicode_utils.pyi
typings/setuptools/version.pyi
typings/setuptools/wheel.pyi
typings/setuptools/windows_support.pyi
typings/setuptools/_distutils/__init__.pyi
typings/setuptools/_vendor/__init__.pyi
typings/setuptools/command/__init__.pyi
typings/setuptools/command/easy_install.pyi
typings/setuptools/command/egg_info.pyi
typings/setuptools/command/py36compat.pyi
typings/setuptools/command/sdist.pyi
typings/setuptools/command/setopt.pyi
typings/setuptools/extern/__init__.pyi