Metadata-Version: 2.1
Name: piphyperd
Version: 1.9.10
Summary: A simple python package to leverage pip programmatically.
Home-page: https://gitlab.com/hyperd/piphyperd
Author: hyperd
Author-email: fc@hyperd.sh
License: GPLv3
Project-URL: Documentation, https://gitlab.com/hyperd/piphyperd
Project-URL: Source, https://gitlab.com/hyperd/piphyperd/-/blob/master/README.md
Platform: UNKNOWN
Classifier: Development Status :: 5 - Production/Stable
Classifier: Operating System :: OS Independent
Classifier: Intended Audience :: Developers
Classifier: Intended Audience :: Information Technology
Classifier: Intended Audience :: System Administrators
Classifier: License :: OSI Approved :: GNU General Public License v3 (GPLv3)
Classifier: Programming Language :: Python :: 3
Classifier: Programming Language :: Python :: 3.5
Classifier: Programming Language :: Python :: 3.6
Classifier: Programming Language :: Python :: 3.7
Classifier: Programming Language :: Python :: 3.8
Classifier: Natural Language :: English
Classifier: Operating System :: POSIX
Classifier: Topic :: Software Development :: Libraries
Classifier: Topic :: Utilities
Classifier: Environment :: Plugins
Requires-Python: >=3.5.*
